luminaire/__init__.py
luminaire/exploration/__init__.py
luminaire/exploration/data_exploration.py
luminaire/model/__init__.py
luminaire/model/base_model.py
luminaire/model/lad_filtering.py
luminaire/model/lad_structural.py
luminaire/model/model_utils.py
luminaire/model/window_density.py
luminaire/optimization/__init__.py
luminaire/optimization/hyperparameter_optimization.py
luminaire/tests/__init__.py
luminaire/tests/conftest.py
luminaire/tests/test_exploration.py
luminaire/tests/test_hyper.py
luminaire/tests/test_models.py
luminaire/utils/__init__.py
luminaire/utils/random_state_validation.py
luminaire-0.4.3.dist-info/LICENSE.txt
luminaire-0.4.3.dist-info/METADATA
luminaire-0.4.3.dist-info/WHEEL
luminaire-0.4.3.dist-info/top_level.txt
luminaire-0.4.3.dist-info/RECORD
