Metadata-Version: 2.1
Name: luminaire
Version: 0.4.3
Summary: Luminaire is a python package that provides ML driven solutions for monitoring time series data
Home-page: https://zillow.github.io/luminaire
Author: Zillow Group A.I. team
Author-email: luminaire-dev-oss@zillowgroup.com
License: Apache License 2.0
Project-URL: Source, https://github.com/zillow/luminaire
Project-URL: Tracker, https://github.com/zillow/luminaire/issues
Keywords: anomaly-detection outlier-detection forecasting time-series automl
Classifier: Development Status :: 4 - Beta
Classifier: License :: OSI Approved :: Apache Software License
Classifier: Programming Language :: Python :: 3.7
Classifier: Programming Language :: Python :: 3.8
Classifier: Programming Language :: Python :: 3.9
Classifier: Programming Language :: Python :: 3.10
Classifier: Operating System :: OS Independent
Classifier: Topic :: Scientific/Engineering :: Information Analysis
Classifier: Topic :: Software Development :: Libraries :: Python Modules
Classifier: Intended Audience :: Developers
Classifier: Intended Audience :: Science/Research
Requires-Python: >=3.7
License-File: LICENSE.txt
Requires-Dist: bayescd >=0.4
Requires-Dist: changepy >=0.3.1
Requires-Dist: hyperopt >=0.1.2
Requires-Dist: numpy <=1.22.4,>=1.17.5
Requires-Dist: pandas <=2.0.3,>=0.25.3
Requires-Dist: pykalman >=0.9.5
Requires-Dist: scipy >=1.6.0
Requires-Dist: statsmodels <=0.13.5,>=0.13.0
Requires-Dist: scikit-learn >=0.24.2
Requires-Dist: decorator >=5.1.0
